__init__.py
_lcms2.pyd
pylcms2/__init__.py
pylcms2/_lcms2.c
pylcms2/implementation.py
pylcms2-0.0.21.dist-info/LICENSE
pylcms2-0.0.21.dist-info/METADATA
pylcms2-0.0.21.dist-info/WHEEL
pylcms2-0.0.21.dist-info/top_level.txt
pylcms2-0.0.21.dist-info/RECORD
