Metadata-Version: 2.2
Name: pylcms2
Version: 0.0.21
Summary: Python binding for LittleCMS2 library
Author-email: Roman Kosobrodov <roman@kosobrodov.net>
Project-URL: Homepage, https://github.com/RomanKosobrodov/python-lcms2
Project-URL: Bug Tracker, https://github.com/RomanKosobrodov/python-lcms2/issues
Classifier: Programming Language :: Python :: 3
Classifier: Programming Language :: C
Classifier: License :: OSI Approved :: GNU General Public License v3 (GPLv3)
Classifier: Operating System :: OS Independent
Classifier: Development Status :: 4 - Beta
Classifier: Environment :: Console
Classifier: Topic :: Multimedia :: Graphics :: Graphics Conversion
Requires-Python: >=3.13
License-File: LICENSE
Requires-Dist: numpy>=2.2.2
